symlink_editor/__init__.py
symlink_editor/fuzzy_completer.py
symlink_editor/main.py
symlink_editor-1.1.0.dist-info/entry_points.txt
symlink_editor-1.1.0.dist-info/licenses/LICENSE
symlink_editor-1.1.0.dist-info/WHEEL
symlink_editor-1.1.0.dist-info/METADATA
symlink_editor-1.1.0.dist-info/RECORD
