Metadata-Version: 2.4
Name: symlink-editor
Version: 1.1.0
Summary: A TUI to change the target of a symlink.
Author-email: erzo <erzo@posteo.de>
Requires-Python: >=3.8
Classifier: Environment :: Console
Classifier: License :: OSI Approved :: BSD License
Classifier: Typing :: Typed
License-File: LICENSE
Requires-Dist: prompt_toolkit >= 3.0.52, < 4.0.0
Requires-Dist: confattr >= 1.7.0, < 2.0.0
Project-URL: Bug tracker, https://gitlab.com/erzo/symlink-editor/-/issues
Project-URL: Change log, https://gitlab.com/erzo/symlink-editor/-/tags
Project-URL: Source code, https://gitlab.com/erzo/symlink-editor
